{
  "color": {
    "palette": {
      "primary": {
        "50": {
          "value": "#CCEDEA",
          "type": "color",
          "description": "color.palette.primary.50"
        },
        "100": {
          "value": "#9ADBD6",
          "type": "color",
          "description": "color.palette.primary.100"
        },
        "150": {
          "value": "#67C9C1",
          "type": "color",
          "description": "color.palette.primary.150"
        },
        "200": {
          "value": "#35B7AD",
          "type": "color",
          "description": "color.palette.primary.200"
        },
        "300": {
          "value": "#02A598",
          "type": "color",
          "description": "color.palette.primary.300"
        },
        "400": {
          "value": "{color.palette.primary.base}",
          "type": "color",
          "description": "color.palette.primary.400"
        },
        "500": {
          "value": "#01625B",
          "type": "color",
          "description": "color.palette.primary.500"
        },
        "600": {
          "value": "#014E48",
          "type": "color",
          "description": "color.palette.primary.600"
        },
        "700": {
          "value": "#003A36",
          "type": "color",
          "description": "color.palette.primary.700"
        },
        "800": {
          "value": "#002623",
          "type": "color",
          "description": "color.palette.primary.800"
        },
        "900": {
          "value": "#001311",
          "type": "color",
          "description": "color.palette.primary.900"
        },
        "base": {
          "value": "#01766D",
          "type": "color",
          "description": "color.palette.primary.base"
        }
      },
      "accent": {
        "50": {
          "value": "#FDF3E0",
          "type": "color",
          "description": "color.palette.accent.50"
        },
        "100": {
          "value": "#FAE7BE",
          "type": "color",
          "description": "color.palette.accent.100"
        },
        "150": {
          "value": "#F8DA9C",
          "type": "color",
          "description": "color.palette.accent.150"
        },
        "200": {
          "value": "#F6CD7A",
          "type": "color",
          "description": "color.palette.accent.200"
        },
        "300": {
          "value": "#F3C159",
          "type": "color",
          "description": "color.palette.accent.300"
        },
        "400": {
          "value": "{color.palette.accent.base}",
          "type": "color",
          "description": "color.palette.accent.400"
        },
        "500": {
          "value": "#C8962E",
          "type": "color",
          "description": "color.palette.accent.500"
        },
        "600": {
          "value": "#A07724",
          "type": "color",
          "description": "color.palette.accent.600"
        },
        "700": {
          "value": "#77591B",
          "type": "color",
          "description": "color.palette.accent.700"
        },
        "800": {
          "value": "#4E3B12",
          "type": "color",
          "description": "color.palette.accent.800"
        },
        "900": {
          "value": "#261C09",
          "type": "color",
          "description": "color.palette.accent.900"
        },
        "base": {
          "value": "#F1B437",
          "type": "color",
          "description": "color.palette.accent.base"
        }
      },
      "neutral": {
        "50": {
          "value": "#F6F8F8",
          "type": "color",
          "description": "color.palette.neutral.50"
        },
        "100": {
          "value": "#EEEEEE",
          "type": "color",
          "description": "color.palette.neutral.100"
        },
        "150": {
          "value": "#CACBCB",
          "type": "color",
          "description": "color.palette.neutral.150"
        },
        "200": {
          "value": "#BFBFBF",
          "type": "color",
          "description": "color.palette.neutral.200"
        },
        "300": {
          "value": "#9D9F9F",
          "type": "color",
          "description": "color.palette.neutral.300"
        },
        "400": {
          "value": "#8D8D8D",
          "type": "color",
          "description": "color.palette.neutral.400"
        },
        "500": {
          "value": "#717272",
          "type": "color",
          "description": "color.palette.neutral.500"
        },
        "600": {
          "value": "#5D5D5D",
          "type": "color",
          "description": "color.palette.neutral.600"
        },
        "700": {
          "value": "#444545",
          "type": "color",
          "description": "color.palette.neutral.700"
        },
        "800": {
          "value": "#323232",
          "type": "color",
          "description": "color.palette.neutral.800"
        },
        "900": {
          "value": "#181818",
          "type": "color",
          "description": "color.palette.neutral.900"
        },
        "base": {
          "value": "#323232",
          "type": "color",
          "description": "color.palette.neutral.base"
        }
      },
      "info": {
        "50": {
          "value": "#E6F1FB",
          "type": "color",
          "description": "color.palette.info.50"
        },
        "100": {
          "value": "#ACD2F5",
          "type": "color",
          "description": "color.palette.info.100"
        },
        "150": {
          "value": "#81BAEF",
          "type": "color",
          "description": "color.palette.info.150"
        },
        "200": {
          "value": "#56A3EA",
          "type": "color",
          "description": "color.palette.info.200"
        },
        "300": {
          "value": "#2B8BE4",
          "type": "color",
          "description": "color.palette.info.300"
        },
        "400": {
          "value": "{color.palette.info.base}",
          "type": "color",
          "description": "color.palette.info.400"
        },
        "500": {
          "value": "#0060B9",
          "type": "color",
          "description": "color.palette.info.500"
        },
        "600": {
          "value": "#004D94",
          "type": "color",
          "description": "color.palette.info.600"
        },
        "700": {
          "value": "#002F62",
          "type": "color",
          "description": "color.palette.info.700"
        },
        "800": {
          "value": "#002649",
          "type": "color",
          "description": "color.palette.info.800"
        },
        "900": {
          "value": "#001223",
          "type": "color",
          "description": "color.palette.info.900"
        },
        "base": {
          "value": "#0074DF",
          "type": "color",
          "description": "color.palette.info.base"
        }
      },
      "success": {
        "50": {
          "value": "#D7F0E7",
          "type": "color",
          "description": "color.palette.success.50"
        },
        "100": {
          "value": "#ADE0CE",
          "type": "color",
          "description": "color.palette.success.100"
        },
        "150": {
          "value": "#82D1B4",
          "type": "color"
        },
        "200": {
          "value": "#58C19B",
          "type": "color",
          "description": "color.palette.success.200"
        },
        "300": {
          "value": "#2DB181",
          "type": "color",
          "description": "color.palette.success.300"
        },
        "400": {
          "value": "#03A168",
          "type": "color",
          "description": "color.palette.success.400"
        },
        "500": {
          "value": "#028656",
          "type": "color",
          "description": "color.palette.success.500"
        },
        "600": {
          "value": "#026B45",
          "type": "color",
          "description": "color.palette.success.600"
        },
        "700": {
          "value": "#015033",
          "type": "color",
          "description": "color.palette.success.700"
        },
        "800": {
          "value": "#013422",
          "type": "color",
          "description": "color.palette.success.800"
        },
        "900": {
          "value": "#001910",
          "type": "color",
          "description": "color.palette.success.900"
        },
        "base": {
          "value": "#03A168",
          "type": "color",
          "description": "color.palette.success.base"
        }
      },
      "warning": {
        "50": {
          "value": "#FEEDD7",
          "type": "color",
          "description": "color.palette.warning.50"
        },
        "100": {
          "value": "#FEDAAC",
          "type": "color",
          "description": "color.palette.warning.100"
        },
        "150": {
          "value": "#FDC681",
          "type": "color",
          "description": "color.palette.warning.150"
        },
        "200": {
          "value": "#FCB356",
          "type": "color",
          "description": "color.palette.warning.200"
        },
        "300": {
          "value": "#FC9F2B",
          "type": "color",
          "description": "color.palette.warning.300"
        },
        "400": {
          "value": "#FB8C00",
          "type": "color",
          "description": "color.palette.warning.400"
        },
        "500": {
          "value": "#D17400",
          "type": "color",
          "description": "color.palette.warning.500"
        },
        "600": {
          "value": "#A65D00",
          "type": "color",
          "description": "color.palette.warning.600"
        },
        "700": {
          "value": "#7C4500",
          "type": "color",
          "description": "color.palette.warning.700"
        },
        "800": {
          "value": "#522E00",
          "type": "color",
          "description": "color.palette.warning.800"
        },
        "900": {
          "value": "#271600",
          "type": "color",
          "description": "color.palette.warning.900"
        },
        "base": {
          "value": "#FB8C00",
          "type": "color",
          "description": "color.palette.warning.base"
        }
      },
      "danger": {
        "50": {
          "value": "#FCDADA",
          "type": "color",
          "description": "color.palette.danger.50"
        },
        "100": {
          "value": "#F9B2B2",
          "type": "color",
          "description": "color.palette.danger.100"
        },
        "150": {
          "value": "#F68989",
          "type": "color",
          "description": "color.palette.danger.150"
        },
        "200": {
          "value": "#F36161",
          "type": "color",
          "description": "color.palette.danger.200"
        },
        "300": {
          "value": "#F03939",
          "type": "color",
          "description": "color.palette.danger.300"
        },
        "400": {
          "value": "#ED1111",
          "type": "color",
          "description": "color.palette.danger.400"
        },
        "500": {
          "value": "#C50E0E",
          "type": "color",
          "description": "color.palette.danger.500"
        },
        "600": {
          "value": "#9D0B0B",
          "type": "color",
          "description": "color.palette.danger.600"
        },
        "700": {
          "value": "#750808",
          "type": "color",
          "description": "color.palette.danger.700"
        },
        "800": {
          "value": "#4D0606",
          "type": "color",
          "description": "color.palette.danger.800"
        },
        "900": {
          "value": "#250303",
          "type": "color",
          "description": "color.palette.danger.900"
        },
        "base": {
          "value": "#ED1111",
          "type": "color",
          "description": "color.palette.danger.base"
        }
      },
      "black": {
        "base": {
          "value": "#323232",
          "type": "color",
          "description": "color.palette.black.base"
        }
      },
      "white": {
        "base": {
          "value": "#FFFFFF",
          "type": "color",
          "description": "color.palette.white.base"
        }
      },
      "transparent": {
        "base": {
          "value": "#00000000",
          "type": "color",
          "description": "color.palette.transparent.base"
        }
      }
    }
  }
}